ihela_client/__init__.py
ihela_client/client.py
ihela_client/merchant_authorization.py
ihela_client/merchant_client.py
ihela_python_client-0.0.4.dist-info/LICENSE
ihela_python_client-0.0.4.dist-info/METADATA
ihela_python_client-0.0.4.dist-info/WHEEL
ihela_python_client-0.0.4.dist-info/top_level.txt
ihela_python_client-0.0.4.dist-info/RECORD
